MANIFEST.in
README.rst
setup.py
nymms/__init__.py
nymms/daemon.py
nymms/exceptions.py
nymms/registry.py
nymms/resources.py
nymms.egg-info/PKG-INFO
nymms.egg-info/SOURCES.txt
nymms.egg-info/dependency_links.txt
nymms.egg-info/requires.txt
nymms.egg-info/top_level.txt
nymms/api/__init__.py
nymms/api/routes.py
nymms/api/plugins/__init__.py
nymms/api/plugins/sdb_handler.py
nymms/config/__init__.py
nymms/config/config.py
nymms/config/yaml_config.py
nymms/config/tests/__init__.py
nymms/config/tests/test_yaml_config.py
nymms/probe/Probe.py
nymms/probe/__init__.py
nymms/probe/sqs_probe.py
nymms/probe/tests/__init__.py
nymms/probe/tests/test_probe.py
nymms/providers/__init__.py
nymms/providers/sdb.py
nymms/reactor/Reactor.py
nymms/reactor/__init__.py
nymms/reactor/aws_reactor.py
nymms/reactor/filters/__init__.py
nymms/reactor/filters/tests/__init__.py
nymms/reactor/handlers/Handler.py
nymms/reactor/handlers/__init__.py
nymms/reactor/handlers/log_handler.py
nymms/reactor/handlers/pagerduty_handler.py
nymms/reactor/handlers/sdb_handler.py
nymms/reactor/handlers/ses_handler.py
nymms/reactor/tests/__init__.py
nymms/reactor/tests/test_reactor.py
nymms/scheduler/Scheduler.py
nymms/scheduler/__init__.py
nymms/scheduler/aws_scheduler.py
nymms/scheduler/backends/Backend.py
nymms/scheduler/backends/__init__.py
nymms/scheduler/backends/yaml_backend.py
nymms/scheduler/lock/SDBLock.py
nymms/scheduler/lock/SchedulerLock.py
nymms/scheduler/lock/__init__.py
nymms/scheduler/lock/tests/__init__.py
nymms/scheduler/lock/tests/test_scheduler_lock.py
nymms/schemas/__init__.py
nymms/schemas/types/__init__.py
nymms/state/State.py
nymms/state/__init__.py
nymms/state/sdb_state.py
nymms/suppress/__init__.py
nymms/suppress/sdb_suppress.py
nymms/suppress/suppress.py
nymms/suppress/tests/__init__.py
nymms/suppress/tests/test_suppression_manager.py
nymms/tests/__init__.py
nymms/tests/test_registry.py
nymms/tests/test_resources.py
nymms/utils/__init__.py
nymms/utils/aws_helper.py
nymms/utils/cli.py
nymms/utils/commands.py
nymms/utils/logutil.py
nymms/utils/templates.py
nymms/utils/tests/__init__.py
nymms/utils/tests/test_base.py
