Metadata-Version: 1.1
Name: nymms
Version: 0.5.0
Summary: Not Your Mother's Monitoring System (NYMMS)
Home-page: https://github.com/cloudtools/nymms
Author: Michael Barrett
Author-email: loki77@gmail.com
License: New BSD license
Platform: UNKNOWN
Classifier: Topic :: System :: Monitoring
Classifier: License :: OSI Approved :: BSD License
Classifier: Development Status :: 3 - Alpha
